rokon/RNet.py
rokon/__init__.py
rokon/model_loader.py
rokon-3.0.4.dist-info/METADATA
rokon-3.0.4.dist-info/WHEEL
rokon-3.0.4.dist-info/top_level.txt
rokon-3.0.4.dist-info/RECORD
